vietnam_number/__init__.py
vietnam_number/number2word/__init__.py
vietnam_number/number2word/data.py
vietnam_number/number2word/hundreds.py
vietnam_number/number2word/large_number.py
vietnam_number/number2word/single.py
vietnam_number/number2word/units.py
vietnam_number/number2word/utils/__init__.py
vietnam_number/number2word/utils/base.py
vietnam_number/word2number/__init__.py
vietnam_number/word2number/couple.py
vietnam_number/word2number/data.py
vietnam_number/word2number/hundreds.py
vietnam_number/word2number/large_number.py
vietnam_number/word2number/single.py
vietnam_number/word2number/tens.py
vietnam_number/word2number/units.py
vietnam_number/word2number/utils/__init__.py
vietnam_number/word2number/utils/base.py
vietnam_number/word2number/utils/hundreds.py
vietnam_number/word2number/utils/large_number.py
vietnam_number/word2number/utils/tens.py
vietnam_number-1.0.5.dist-info/METADATA
vietnam_number-1.0.5.dist-info/WHEEL
vietnam_number-1.0.5.dist-info/RECORD
