Metadata-Version: 2.3
Name: vietnam_number
Version: 1.0.5
Summary: Thư viện xữ lý chữ số dành riêng cho Tiếng Việt - Hỗ trợ chuyển đổi cho cả văn nói và văn viết
License: GPL-3.0-or-later
Keywords: Vietnam,number,w2n,n2w,number to word,word to number,text to number,number to text
Author: Nguyễn Hoài Thương
Author-email: ng.thuong.lio@gmail.com
Requires-Python: >=3.9,<4.0
Classifier: Intended Audience :: Developers
Classifier: Intended Audience :: Financial and Insurance Industry
Classifier: Intended Audience :: Information Technology
Classifier: Intended Audience :: Telecommunications Industry
Classifier: License :: OSI Approved :: GNU General Public License v3 or later (GPLv3+)
Classifier: Natural Language :: Vietnamese
Classifier: Operating System :: OS Independent
Classifier: Programming Language :: Python :: 3
Classifier: Programming Language :: Python :: 3.9
Classifier: Programming Language :: Python :: 3.10
Classifier: Programming Language :: Python :: 3.11
Classifier: Programming Language :: Python :: 3.12
Classifier: Programming Language :: Python :: 3.13
Classifier: Programming Language :: Python :: 3 :: Only
Classifier: Topic :: Software Development :: Libraries :: Python Modules
Classifier: Topic :: Software Development :: Localization
Classifier: Topic :: Software Development :: Quality Assurance
Project-URL: Repository, https://github.com/ngthuong45/vietnam-number.git
